mlua/__init__.py
mlua/cores.py
mlua/envs.py
mlua/errors.py
mlua/roots.py
mlua-1.0.5.dist-info/LICENSE
mlua-1.0.5.dist-info/METADATA
mlua-1.0.5.dist-info/WHEEL
mlua-1.0.5.dist-info/top_level.txt
mlua-1.0.5.dist-info/RECORD
