Metadata-Version: 2.2
Name: mlua
Version: 1.0.5
Summary: 一个基于 lupa 模块的轻量级扩展库，提供了便捷的 Lua 模块加载与管理功能。
Home-page: https://github.com/FreeStar007/mlua
Author: FreeStar007
Author-email: 3089666858@qq.com
License: Apache-2.0
Classifier: Programming Language :: Python :: 3
Classifier: Operating System :: OS Independent
Requires-Python: >=3.10
License-File: LICENSE
Requires-Dist: lupa
Requires-Dist: colorama
Dynamic: author
Dynamic: author-email
Dynamic: classifier
Dynamic: description
Dynamic: description-content-type
Dynamic: home-page
Dynamic: license
Dynamic: requires-dist
Dynamic: requires-python
Dynamic: summary
